README.txt
setup.py
model_tool/__init__.py
model_tool/feature_sel.py
model_tool/model_eva.py
model_tool_td.egg-info/PKG-INFO
model_tool_td.egg-info/SOURCES.txt
model_tool_td.egg-info/dependency_links.txt
model_tool_td.egg-info/top_level.txt
model_tool_td.egg-info/zip-safe