Metadata-Version: 1.1
Name: model-tool-td
Version: 1.0.3
Summary: this is a test package for packing python liberaries tutorial.
Home-page: http://blog.useasp.net/
Author: test
Author-email: test@XXX.cn
License: MIT
Keywords: test python package
Platform: UNKNOWN
Classifier: License :: OSI Approved :: MIT License
Classifier: Programming Language :: Python
Classifier: Intended Audience :: Developers
Classifier: Operating System :: OS Independent
